dictionary/__init__.py
dictionary/dictionary.py
q1q1_dictionary-2.0.0.dist-info/METADATA
q1q1_dictionary-2.0.0.dist-info/WHEEL
q1q1_dictionary-2.0.0.dist-info/top_level.txt
q1q1_dictionary-2.0.0.dist-info/RECORD
